abstract_python/__init__.py
abstract_python/abstract.py
abstract_python-0.1.4.dist-info/METADATA
abstract_python-0.1.4.dist-info/WHEEL
abstract_python-0.1.4.dist-info/RECORD
