Metadata-Version: 2.1
Name: abstract-python
Version: 0.1.4
Summary: A wrapper for all AbstractAPI APIs
Home-page: https://github.com/Omotunde2005/abstractpython.git
License: MIT
Author: Edun Rilwan
Author-email: edunrilwan@gmail.com
Requires-Python: >=3.8
Classifier: License :: OSI Approved :: MIT License
Classifier: Programming Language :: Python :: 3
Classifier: Programming Language :: Python :: 3.8
Classifier: Programming Language :: Python :: 3.9
Classifier: Programming Language :: Python :: 3.10
Classifier: Programming Language :: Python :: 3.11
Classifier: Programming Language :: Python :: 3.12
Requires-Dist: pytest (>=7.4.0)
Requires-Dist: requests (>=2.32.2)
Project-URL: Repository, https://github.com/Omotunde2005/abstractpython.git
